LICENSE.txt
MANIFEST.in
README.rst
setup.py
twss/__init__.py
twss/negative.txt
twss/positive.txt
twss/twsslib.py
twss.egg-info/PKG-INFO
twss.egg-info/SOURCES.txt
twss.egg-info/dependency_links.txt
twss.egg-info/not-zip-safe
twss.egg-info/requires.txt
twss.egg-info/top_level.txt