Metadata-Version: 1.0
Name: twss
Version: 0.1.8
Summary: TWSS: A Naive Bayes classifier that can identify double entendres.
Home-page: https://github.com/sengupta/twss
Author: Aditya Sengupta
Author-email: aditya@sengupta.me
License: 
